ug_python_sdk/__init__.py
ug_python_sdk/client/__init__.py
ug_python_sdk/client/admin_client.py
ug_python_sdk/client/client.py
ug_python_sdk/client/oauth.py
ug_python_sdk/client/py.typed
ug_python_sdk/client/session.py
ug_python_sdk/configs.py
ug_python_sdk/messages.py
ug_python_sdk/py.typed
ug_python_sdk/rpc/__init__.py
ug_python_sdk/rpc/channel.py
ug_python_sdk/rpc/rpc.py
ug_python_sdk/rpc/utils.py
ug_python_sdk/rpc/websocket.py
ug_python_sdk/speech.py
ug_python_sdk/types.py
ug_python_sdk/utilities.py
ug_python_sdk-3.0.3.dist-info/METADATA
ug_python_sdk-3.0.3.dist-info/WHEEL
ug_python_sdk-3.0.3.dist-info/RECORD
