Metadata-Version: 2.3
Name: ug-python-sdk
Version: 3.0.3
Summary: Python SDK for the UG AI Platform
Author: UG Labs
Author-email: support@uglabs.io
Requires-Python: >=3.12
Classifier: Programming Language :: Python :: 3
Classifier: Programming Language :: Python :: 3.12
Classifier: Programming Language :: Python :: 3.13
Requires-Dist: aiohttp (>=3.13.3,<4.0.0)
Requires-Dist: httpx (>=0.28.1,<0.29.0)
Requires-Dist: pydantic (>=2.11.7,<3.0.0)
Requires-Dist: websockets (>=15.0.1,<16.0.0)
